dualsoundsync/YaLTCdemodulation.py
dualsoundsync/__init__.py
dualsoundsync/__main__.py
dualsoundsync/__main__OLD.py
dualsoundsync/dss.py
dualsoundsync/dualsoundsync.py
dualsoundsync/file_io.py
dualsoundsync-0.1.3.dist-info/LICENSE
dualsoundsync-0.1.3.dist-info/METADATA
dualsoundsync-0.1.3.dist-info/WHEEL
dualsoundsync-0.1.3.dist-info/entry_points.txt
dualsoundsync-0.1.3.dist-info/top_level.txt
dualsoundsync-0.1.3.dist-info/RECORD
