Metadata-Version: 2.1
Name: dualsoundsync
Version: 0.1.3
Summary: Python command line for syncing audio video recordings with YaLTC tracks.
Home-page: https://git.sr.ht/~proflutz/dualsoundsync
Author: Raymond Lutz
Author-email: lutzray@mac.com
License: UNKNOWN
Platform: UNKNOWN
Classifier: Development Status :: 2 - Pre-Alpha
Classifier: Environment :: Console
Classifier: Intended Audience :: End Users/Desktop
Classifier: License :: OSI Approved :: MIT License
Classifier: Operating System :: MacOS
Classifier: Operating System :: Microsoft :: Windows
Classifier: Operating System :: POSIX
Classifier: Programming Language :: Python :: 3
Classifier: Topic :: Multimedia :: Sound/Audio
Classifier: Topic :: Utilities
Classifier: Topic :: Multimedia :: Sound/Audio :: Capture/Recording
Classifier: Topic :: Multimedia :: Video :: Non-Linear Editor
License-File: LICENSE
Requires-Dist: ffmpeg (==1.4)
Requires-Dist: loguru (==0.5.3)
Requires-Dist: matplotlib (==3.4.3)
Requires-Dist: numpy (==1.20.3)
Requires-Dist: PyYAML (==6.0)
Requires-Dist: rich (==10.12.0)
Requires-Dist: scipy (==1.7.1)
